redevelop_elyra/__init__.py
redevelop_elyra/_version.py
redevelop_elyra-0.1.1.data/data/share/jupyter/labextensions/redevelop-elyra/package.json
redevelop_elyra-0.1.1.data/data/share/jupyter/labextensions/redevelop-elyra/schemas/redevelop-elyra/package.json.orig
redevelop_elyra-0.1.1.data/data/share/jupyter/labextensions/redevelop-elyra/schemas/redevelop-elyra/plugin.json
redevelop_elyra-0.1.1.data/data/share/jupyter/labextensions/redevelop-elyra/static/117.dcde89b91bc8b8b2ccf2.js
redevelop_elyra-0.1.1.data/data/share/jupyter/labextensions/redevelop-elyra/static/117.dcde89b91bc8b8b2ccf2.js.LICENSE.txt
redevelop_elyra-0.1.1.data/data/share/jupyter/labextensions/redevelop-elyra/static/126.e5b009cc20d9ab98a646.js
redevelop_elyra-0.1.1.data/data/share/jupyter/labextensions/redevelop-elyra/static/155.99cde2ecb7ff03222e9b.js
redevelop_elyra-0.1.1.data/data/share/jupyter/labextensions/redevelop-elyra/static/165.1f51e28daea6e5fd4444.js
redevelop_elyra-0.1.1.data/data/share/jupyter/labextensions/redevelop-elyra/static/170.aed326c126dfee911bd8.js
redevelop_elyra-0.1.1.data/data/share/jupyter/labextensions/redevelop-elyra/static/170.aed326c126dfee911bd8.js.LICENSE.txt
redevelop_elyra-0.1.1.data/data/share/jupyter/labextensions/redevelop-elyra/static/224.a3930976144b8f122b3d.js
redevelop_elyra-0.1.1.data/data/share/jupyter/labextensions/redevelop-elyra/static/251.626d52f76538730e0b60.js
redevelop_elyra-0.1.1.data/data/share/jupyter/labextensions/redevelop-elyra/static/251.626d52f76538730e0b60.js.LICENSE.txt
redevelop_elyra-0.1.1.data/data/share/jupyter/labextensions/redevelop-elyra/static/286.8ea7c166625510a16e53.js
redevelop_elyra-0.1.1.data/data/share/jupyter/labextensions/redevelop-elyra/static/326.f108c8472da52041c979.js
redevelop_elyra-0.1.1.data/data/share/jupyter/labextensions/redevelop-elyra/static/398.1536e12269961c7f883f.js
redevelop_elyra-0.1.1.data/data/share/jupyter/labextensions/redevelop-elyra/static/398.1536e12269961c7f883f.js.LICENSE.txt
redevelop_elyra-0.1.1.dist-info/METADATA
redevelop_elyra-0.1.1.dist-info/WHEEL
redevelop_elyra-0.1.1.dist-info/licenses/LICENSE
redevelop_elyra-0.1.1.dist-info/RECORD
